kyu_ml/__init__.py
kyu_ml/example.py
kyu_ml-0.0.1.dist-info/LICENSE
kyu_ml-0.0.1.dist-info/METADATA
kyu_ml-0.0.1.dist-info/WHEEL
kyu_ml-0.0.1.dist-info/top_level.txt
kyu_ml-0.0.1.dist-info/RECORD
