Metadata-Version: 2.1
Name: kyu-ml
Version: 0.0.1
Summary: personal library
Home-page: https://github.com/kyu90/kyu_personal
Author: kyunam
Author-email: rbska56455@gmail.com
Project-URL: Bug Tracker, https://github.com/kyu90/kyu_personal/issues
Classifier: Programming Language :: Python :: 3
Classifier: License :: OSI Approved :: MIT License
Classifier: Operating System :: OS Independent
Requires-Python: >=3.6
License-File: LICENSE
